pytexttosql/__init__.py
pytexttosql/mongodb/__init__.py
pytexttosql/sqlite/__init__.py
pytexttosql/sqlite/handlers/__init__.py
pytexttosql/sqlite/handlers/database/__init__.py
pytexttosql/sqlite/handlers/database/handler.py
pytexttosql/sqlite/handlers/llm/__init__.py
pytexttosql/sqlite/handlers/llm/handler.py
pytexttosql/sqlite/handlers/query/__init__.py
pytexttosql/sqlite/handlers/query/handler.py
pytexttosql-0.0.9.dist-info/LICENSE
pytexttosql-0.0.9.dist-info/METADATA
pytexttosql-0.0.9.dist-info/WHEEL
pytexttosql-0.0.9.dist-info/top_level.txt
pytexttosql-0.0.9.dist-info/RECORD
